avoidbench.cp36-win_amd64.pyd
avoidbench-0.1.7.dist-info/METADATA
avoidbench-0.1.7.dist-info/WHEEL
avoidbench-0.1.7.dist-info/top_level.txt
avoidbench-0.1.7.dist-info/RECORD
