Metadata-Version: 2.1
Name: avoidbench
Version: 0.1.7
Summary: Python client for the UE4 avoidbench benchmark simulator
Home-page: https://github.com/RanoVeder/AvoidBench
Author: Rano Veder
Author-email: rano.veder@gmail.com
License: MIT
Platform: UNKNOWN
